cpr/__init__.py
cpr/critical_values.py
cpr/fmols.py
cpr/lr_variance.py
cpr/poly_terms.py
cpr/tests.py
cpr/utils.py
cpr_econometrics-0.0.2.dist-info/licenses/LICENSE
cpr_econometrics-0.0.2.dist-info/METADATA
cpr_econometrics-0.0.2.dist-info/WHEEL
cpr_econometrics-0.0.2.dist-info/top_level.txt
cpr_econometrics-0.0.2.dist-info/RECORD
